{
    "errors": [
        "SYMBOLIC EXECUTION TIMEOUT"
    ],
    "fails": [],
    "findings": [
        {
            "column": 14,
            "contract": "Government",
            "filename": "smartbugs_all/list_dos.sol",
            "line": 37,
            "name": "Callstack bug"
        },
        {
            "column": 14,
            "contract": "Government",
            "filename": "smartbugs_all/list_dos.sol",
            "line": 39,
            "name": "Callstack bug"
        },
        {
            "column": 14,
            "contract": "Government",
            "filename": "smartbugs_all/list_dos.sol",
            "line": 40,
            "name": "Callstack bug"
        },
        {
            "column": 18,
            "contract": "Government",
            "filename": "smartbugs_all/list_dos.sol",
            "line": 62,
            "name": "Callstack bug"
        },
        {
            "column": 22,
            "contract": "Government",
            "filename": "smartbugs_all/list_dos.sol",
            "line": 70,
            "name": "Callstack bug"
        },
        {
            "column": 22,
            "contract": "Government",
            "filename": "smartbugs_all/list_dos.sol",
            "line": 75,
            "name": "Callstack bug"
        },
        {
            "column": 14,
            "contract": "Government",
            "filename": "smartbugs_all/list_dos.sol",
            "line": 37,
            "name": "Concurrency bug"
        },
        {
            "column": 14,
            "contract": "Government",
            "filename": "smartbugs_all/list_dos.sol",
            "line": 39,
            "name": "Concurrency bug"
        },
        {
            "column": 14,
            "contract": "Government",
            "filename": "smartbugs_all/list_dos.sol",
            "line": 40,
            "name": "Concurrency bug"
        },
        {
            "column": 18,
            "contract": "Government",
            "filename": "smartbugs_all/list_dos.sol",
            "line": 82,
            "name": "Concurrency bug"
        },
        {
            "column": 14,
            "contract": "Government",
            "filename": "smartbugs_all/list_dos.sol",
            "line": 35,
            "name": "Overflow bugs"
        },
        {
            "column": 14,
            "contract": "Government",
            "filename": "smartbugs_all/list_dos.sol",
            "line": 95,
            "name": "Overflow bugs"
        },
        {
            "column": 14,
            "contract": "Government",
            "filename": "smartbugs_all/list_dos.sol",
            "line": 101,
            "name": "Overflow bugs"
        },
        {
            "column": 6,
            "contract": "Government",
            "filename": "smartbugs_all/list_dos.sol",
            "line": 117,
            "name": "Overflow bugs"
        },
        {
            "column": 10,
            "contract": "Government",
            "filename": "smartbugs_all/list_dos.sol",
            "line": 118,
            "name": "Overflow bugs"
        },
        {
            "column": 10,
            "contract": "Government",
            "filename": "smartbugs_all/list_dos.sol",
            "line": 35,
            "name": "Time dependency bug"
        }
    ],
    "infos": [],
    "parser": {
        "id": "osiris",
        "mode": "solidity",
        "version": "2023/02/27"
    }
}
