{
    "errors": [
        "EXIT_CODE_19"
    ],
    "fails": [],
    "findings": [
        {
            "confidence": "High",
            "filename": "all_contract/MasterChefGoblinConfig_1.sol",
            "impact": "Informational",
            "line": 2,
            "message": "Different versions of Solidity is used in MasterChefGoblinConfig_1.sol:\n\t- Version used: ['ABIEncoderV2', '^0.5.0']\n\t- MasterChefGoblinConfig_1.sol#2 declares pragma solidity^0.5.0\n\t- MasterChefGoblinConfig_1.sol#294 declares pragma experimentalABIEncoderV2\n",
            "name": "pragma"
        },
        {
            "confidence": "High",
            "contract": "Ownable",
            "filename": "all_contract/MasterChefGoblinConfig_1.sol",
            "function": "owner",
            "impact": "Informational",
            "line": 29,
            "line_end": 31,
            "message": "Ownable.owner (MasterChefGoblinConfig_1.sol#29-31) should be declared external\n",
            "name": "external-function"
        },
        {
            "confidence": "High",
            "contract": "Ownable",
            "filename": "all_contract/MasterChefGoblinConfig_1.sol",
            "function": "renounceOwnership",
            "impact": "Informational",
            "line": 55,
            "line_end": 58,
            "message": "Ownable.renounceOwnership (MasterChefGoblinConfig_1.sol#55-58) should be declared external\n",
            "name": "external-function"
        },
        {
            "confidence": "High",
            "contract": "Ownable",
            "filename": "all_contract/MasterChefGoblinConfig_1.sol",
            "function": "transferOwnership",
            "impact": "Informational",
            "line": 64,
            "line_end": 66,
            "message": "Ownable.transferOwnership (MasterChefGoblinConfig_1.sol#64-66) should be declared external\n",
            "name": "external-function"
        },
        {
            "confidence": "High",
            "filename": "all_contract/MasterChefGoblinConfig_1.sol",
            "impact": "Informational",
            "line": 2,
            "message": "Detected issues with version pragma in MasterChefGoblinConfig_1.sol:\n\t- pragma solidity^0.5.0 (MasterChefGoblinConfig_1.sol#2): it allows old versions\n",
            "name": "solc-version"
        },
        {
            "confidence": "High",
            "contract": "SafeToken",
            "filename": "all_contract/MasterChefGoblinConfig_1.sol",
            "function": "safeApprove",
            "impact": "Informational",
            "line": 270,
            "line_end": 274,
            "message": "Low level call in SafeToken.safeApprove (MasterChefGoblinConfig_1.sol#270-274):\n\t-(success,data) = token.call(abi.encodeWithSelector(0x095ea7b3,to,value)) MasterChefGoblinConfig_1.sol#272\n",
            "name": "low-level-calls"
        },
        {
            "confidence": "High",
            "contract": "SafeToken",
            "filename": "all_contract/MasterChefGoblinConfig_1.sol",
            "function": "safeTransfer",
            "impact": "Informational",
            "line": 276,
            "line_end": 280,
            "message": "Low level call in SafeToken.safeTransfer (MasterChefGoblinConfig_1.sol#276-280):\n\t-(success,data) = token.call(abi.encodeWithSelector(0xa9059cbb,to,value)) MasterChefGoblinConfig_1.sol#278\n",
            "name": "low-level-calls"
        },
        {
            "confidence": "High",
            "contract": "SafeToken",
            "filename": "all_contract/MasterChefGoblinConfig_1.sol",
            "function": "safeTransferFrom",
            "impact": "Informational",
            "line": 282,
            "line_end": 286,
            "message": "Low level call in SafeToken.safeTransferFrom (MasterChefGoblinConfig_1.sol#282-286):\n\t-(success,data) = token.call(abi.encodeWithSelector(0x23b872dd,from,to,value)) MasterChefGoblinConfig_1.sol#284\n",
            "name": "low-level-calls"
        },
        {
            "confidence": "High",
            "contract": "SafeToken",
            "filename": "all_contract/MasterChefGoblinConfig_1.sol",
            "function": "safeTransferETH",
            "impact": "Informational",
            "line": 288,
            "line_end": 291,
            "message": "Low level call in SafeToken.safeTransferETH (MasterChefGoblinConfig_1.sol#288-291):\n\t-(success) = to.call.value(value)(new bytes(0)) MasterChefGoblinConfig_1.sol#289\n",
            "name": "low-level-calls"
        },
        {
            "confidence": "High",
            "filename": "all_contract/MasterChefGoblinConfig_1.sol",
            "impact": "Informational",
            "line": 71,
            "line_end": 75,
            "message": "Function 'Ownable._transferOwnership' (MasterChefGoblinConfig_1.sol#71-75) is not in mixedCase\n",
            "name": "naming-convention"
        },
        {
            "confidence": "High",
            "filename": "all_contract/MasterChefGoblinConfig_1.sol",
            "impact": "Informational",
            "line": 201,
            "message": "Function 'IUniswapV2Pair.DOMAIN_SEPARATOR' (MasterChefGoblinConfig_1.sol#201) is not in mixedCase\n",
            "name": "naming-convention"
        },
        {
            "confidence": "High",
            "filename": "all_contract/MasterChefGoblinConfig_1.sol",
            "impact": "Informational",
            "line": 202,
            "message": "Function 'IUniswapV2Pair.PERMIT_TYPEHASH' (MasterChefGoblinConfig_1.sol#202) is not in mixedCase\n",
            "name": "naming-convention"
        },
        {
            "confidence": "High",
            "filename": "all_contract/MasterChefGoblinConfig_1.sol",
            "impact": "Informational",
            "line": 219,
            "message": "Function 'IUniswapV2Pair.MINIMUM_LIQUIDITY' (MasterChefGoblinConfig_1.sol#219) is not in mixedCase\n",
            "name": "naming-convention"
        },
        {
            "confidence": "High",
            "filename": "all_contract/MasterChefGoblinConfig_1.sol",
            "impact": "Informational",
            "line": 234,
            "message": "Parameter '' of IUniswapV2Pair.initialize (MasterChefGoblinConfig_1.sol#234) is not in mixedCase\n",
            "name": "naming-convention"
        },
        {
            "confidence": "High",
            "filename": "all_contract/MasterChefGoblinConfig_1.sol",
            "impact": "Informational",
            "line": 234,
            "message": "Parameter '_scope_0' of IUniswapV2Pair.initialize (MasterChefGoblinConfig_1.sol#234) is not in mixedCase\n",
            "name": "naming-convention"
        },
        {
            "confidence": "High",
            "filename": "all_contract/MasterChefGoblinConfig_1.sol",
            "impact": "Informational",
            "line": 367,
            "message": "Parameter '' of MasterChefGoblinConfig.workFactor (MasterChefGoblinConfig_1.sol#367) is not in mixedCase\n",
            "name": "naming-convention"
        },
        {
            "confidence": "High",
            "filename": "all_contract/MasterChefGoblinConfig_1.sol",
            "impact": "Informational",
            "line": 373,
            "message": "Parameter '' of MasterChefGoblinConfig.killFactor (MasterChefGoblinConfig_1.sol#373) is not in mixedCase\n",
            "name": "naming-convention"
        },
        {
            "confidence": "High",
            "filename": "all_contract/MasterChefGoblinConfig_1.sol",
            "impact": "Informational",
            "line": 314,
            "message": "Parameter '_oracle' of MasterChefGoblinConfig. (MasterChefGoblinConfig_1.sol#314) is not in mixedCase\n",
            "name": "naming-convention"
        },
        {
            "confidence": "High",
            "filename": "all_contract/MasterChefGoblinConfig_1.sol",
            "impact": "Informational",
            "line": 319,
            "message": "Parameter '_oracle' of MasterChefGoblinConfig.setOracle (MasterChefGoblinConfig_1.sol#319) is not in mixedCase\n",
            "name": "naming-convention"
        }
    ],
    "infos": [],
    "parser": {
        "id": "slither",
        "mode": "solidity",
        "version": "2022/11/14"
    }
}
