{
    "errors": [],
    "fails": [
        "DOCKER_SEGV"
    ],
    "findings": [
        {
            "column": 14,
            "contract": "BasicMathLib",
            "filename": "all_contract/InteractiveCrowdsaleLib_1.sol",
            "line": 81,
            "name": "Integer Overflow"
        },
        {
            "column": 21,
            "contract": "BasicMathLib",
            "filename": "all_contract/InteractiveCrowdsaleLib_1.sol",
            "line": 82,
            "name": "Integer Underflow"
        },
        {
            "column": 5,
            "contract": "CrowdsaleToken",
            "filename": "all_contract/InteractiveCrowdsaleLib_1.sol",
            "line": 411,
            "name": "Integer Underflow"
        },
        {
            "column": 12,
            "contract": "TokenLib",
            "filename": "all_contract/InteractiveCrowdsaleLib_1.sol",
            "line": 246,
            "name": "Integer Overflow"
        }
    ],
    "infos": [
        "analysis incomplete"
    ],
    "parser": {
        "id": "oyente",
        "mode": "solidity",
        "version": "2023/02/27"
    }
}
